{
  "appInfo" : {
    "build" : "213.7172.25",
    "buildDate" : "2022-03-15T16:44:10.642Z[UTC]",
    "productCode" : "IC",
    "generated" : "2022-11-17T13:17:21.916076Z",
    "os" : "Linux 6.0.7-200.fc36.x86_64",
    "runtime" : "JetBrains s.r.o. 11.0.14.1 11.0.14.1+1-b1751.46"
  },
  "runtimeInfo" : {
    "maxMemory" : 536870912,
    "numberOfProcessors" : 8,
    "maxNumberOfIndexingThreads" : 4,
    "maxSizeOfFileForIntelliSense" : 2560000,
    "maxSizeOfFileForContentLoading" : 20971520
  },
  "projectIndexingHistory" : {
    "projectName" : "untitled",
    "times" : {
      "indexingReason" : "On project open",
      "wasFullIndexing" : true,
      "totalUpdatingTime" : 3111098426,
      "indexingTime" : 145639000,
      "contentLoadingTime" : 1809189,
      "scanFilesTime" : 2866449000,
      "pushPropertiesTime" : 1234000,
      "indexExtensionsTime" : 0,
      "updatingStart" : "2022-11-17T13:17:18.788731Z",
      "updatingEnd" : "2022-11-17T13:17:21.901662Z",
      "totalSuspendedTime" : 0,
      "wasInterrupted" : false
    },
    "fileCount" : {
      "numberOfFileProviders" : 8,
      "numberOfScannedFiles" : 27330,
      "numberOfFilesIndexedByInfrastructureExtensionsDuringScan" : 0,
      "numberOfFilesScheduledForIndexingAfterScan" : 1,
      "numberOfFilesIndexedByInfrastructureExtensionsDuringIndexingStage" : 0,
      "numberOfFilesIndexedWithLoadingContent" : 1
    },
    "totalStatsPerFileType" : [ {
      "fileType" : "PLAIN_TEXT",
      "partOfTotalProcessingTime" : {
        "part" : 115894706,
        "total" : 115894706
      },
      "partOfTotalContentLoadingTime" : {
        "part" : 1671814,
        "total" : 1671814
      },
      "totalNumberOfFiles" : 1,
      "totalFilesSize" : 85,
      "indexingSpeed" : {
        "totalBytes" : 85,
        "totalTime" : 115894706
      },
      "biggestContributors" : [ {
        "providerName" : "Module 'untitled' (untitled)",
        "numberOfFiles" : 1,
        "totalFilesSize" : 85,
        "partOfTotalProcessingTimeOfThisFileType" : {
          "part" : 115894706,
          "total" : 115894706
        }
      } ]
    } ],
    "totalStatsPerIndexer" : [ {
      "indexId" : "TodoIndex",
      "partOfTotalIndexingTime" : {
        "part" : 79043523,
        "total" : 86998890
      },
      "totalNumberOfFiles" : 1,
      "totalNumberOfFilesIndexedByExtensions" : 0,
      "totalFilesSize" : 85,
      "indexingSpeed" : {
        "totalBytes" : 85,
        "totalTime" : 79043523
      },
      "snapshotInputMappingStats" : {
        "totalRequests" : 0,
        "totalMisses" : 0,
        "totalHits" : 0
      }
    }, {
      "indexId" : "IdIndex",
      "partOfTotalIndexingTime" : {
        "part" : 5502340,
        "total" : 86998890
      },
      "totalNumberOfFiles" : 1,
      "totalNumberOfFilesIndexedByExtensions" : 0,
      "totalFilesSize" : 85,
      "indexingSpeed" : {
        "totalBytes" : 85,
        "totalTime" : 5502340
      },
      "snapshotInputMappingStats" : {
        "totalRequests" : 0,
        "totalMisses" : 0,
        "totalHits" : 0
      }
    }, {
      "indexId" : "Trigram.Index",
      "partOfTotalIndexingTime" : {
        "part" : 2453027,
        "total" : 86998890
      },
      "totalNumberOfFiles" : 1,
      "totalNumberOfFilesIndexedByExtensions" : 0,
      "totalFilesSize" : 85,
      "indexingSpeed" : {
        "totalBytes" : 85,
        "totalTime" : 2453027
      },
      "snapshotInputMappingStats" : {
        "totalRequests" : 0,
        "totalMisses" : 0,
        "totalHits" : 0
      }
    } ],
    "scanningStatistics" : [ {
      "providerName" : "JDK 17",
      "numberOfScannedFiles" : 27100,
      "numberOfSkippedFiles" : 0,
      "numberOfFilesForIndexing" : 0,
      "numberOfFilesFullyIndexedByInfrastructureExtensions" : 0,
      "scanningTime" : 1864700316,
      "timeProcessingUpToDateFiles" : 0,
      "timeUpdatingContentLessIndexes" : 60779319,
      "timeIndexingWithoutContent" : 0
    }, {
      "providerName" : "Indexable set contributor 'com.intellij.javaee.ExternalResourcesRootsProvider@20dd5bd2' (non-project)",
      "numberOfScannedFiles" : 224,
      "numberOfSkippedFiles" : 4,
      "numberOfFilesForIndexing" : 0,
      "numberOfFilesFullyIndexedByInfrastructureExtensions" : 0,
      "scanningTime" : 251670519,
      "timeProcessingUpToDateFiles" : 0,
      "timeUpdatingContentLessIndexes" : 3439458,
      "timeIndexingWithoutContent" : 0
    }, {
      "providerName" : "Module 'untitled' (untitled)",
      "numberOfScannedFiles" : 6,
      "numberOfSkippedFiles" : 0,
      "numberOfFilesForIndexing" : 1,
      "numberOfFilesFullyIndexedByInfrastructureExtensions" : 0,
      "scanningTime" : 52649978,
      "timeProcessingUpToDateFiles" : 0,
      "timeUpdatingContentLessIndexes" : 38863834,
      "timeIndexingWithoutContent" : 3079769
    }, {
      "providerName" : "Indexable set contributor 'com.intellij.javaee.ExternalResourcesRootsProvider@20dd5bd2' (project)",
      "numberOfScannedFiles" : 0,
      "numberOfSkippedFiles" : 0,
      "numberOfFilesForIndexing" : 0,
      "numberOfFilesFullyIndexedByInfrastructureExtensions" : 0,
      "scanningTime" : 0,
      "timeProcessingUpToDateFiles" : 0,
      "timeUpdatingContentLessIndexes" : 0,
      "timeIndexingWithoutContent" : 0
    }, {
      "providerName" : "Indexable set contributor 'Kotlin Script dependencies' (non-project)",
      "numberOfScannedFiles" : 0,
      "numberOfSkippedFiles" : 0,
      "numberOfFilesForIndexing" : 0,
      "numberOfFilesFullyIndexedByInfrastructureExtensions" : 0,
      "scanningTime" : 0,
      "timeProcessingUpToDateFiles" : 0,
      "timeUpdatingContentLessIndexes" : 0,
      "timeIndexingWithoutContent" : 0
    }, {
      "providerName" : "Indexable set contributor 'Scratches & Consoles' (non-project)",
      "numberOfScannedFiles" : 0,
      "numberOfSkippedFiles" : 0,
      "numberOfFilesForIndexing" : 0,
      "numberOfFilesFullyIndexedByInfrastructureExtensions" : 0,
      "scanningTime" : 0,
      "timeProcessingUpToDateFiles" : 0,
      "timeUpdatingContentLessIndexes" : 0,
      "timeIndexingWithoutContent" : 0
    }, {
      "providerName" : "Indexable set contributor 'Scratches & Consoles' (project)",
      "numberOfScannedFiles" : 0,
      "numberOfSkippedFiles" : 0,
      "numberOfFilesForIndexing" : 0,
      "numberOfFilesFullyIndexedByInfrastructureExtensions" : 0,
      "scanningTime" : 0,
      "timeProcessingUpToDateFiles" : 0,
      "timeUpdatingContentLessIndexes" : 0,
      "timeIndexingWithoutContent" : 0
    }, {
      "providerName" : "Indexable set contributor 'Kotlin Script dependencies' (project)",
      "numberOfScannedFiles" : 0,
      "numberOfSkippedFiles" : 0,
      "numberOfFilesForIndexing" : 0,
      "numberOfFilesFullyIndexedByInfrastructureExtensions" : 0,
      "scanningTime" : 0,
      "timeProcessingUpToDateFiles" : 0,
      "timeUpdatingContentLessIndexes" : 0,
      "timeIndexingWithoutContent" : 0
    } ],
    "fileProviderStatistics" : [ {
      "providerName" : "Module 'untitled' (untitled)",
      "totalNumberOfIndexedFiles" : 1,
      "totalNumberOfFilesFullyIndexedByExtensions" : 0,
      "totalIndexingTime" : 125417955,
      "contentLoadingTime" : 1809189,
      "numberOfTooLargeForIndexingFiles" : 0,
      "slowIndexedFiles" : [ ]
    } ]
  }
}